tastypie_services
