Metadata-Version: 1.0
Name: tastypie-services
Version: 0.2.2
Summary: Service URLs for tastypie
Home-page: https://github.com/andymckay/tastypie-services
Author: Andy McKay
Author-email: andym@mozilla.com
License: BSD
Platform: UNKNOWN
Classifier: Intended Audience :: Developers
Classifier: Natural Language :: English
Classifier: Operating System :: OS Independent
Classifier: Framework :: Django
